elasticsearch_migrate/__init__.py
elasticsearch_migrate/admin.py
elasticsearch_migrate/apps.py
elasticsearch_migrate/models.py
elasticsearch_migrate/registry.py
elasticsearch_migrate/tests.py
elasticsearch_migrate/views.py
elasticsearch_migrate/management/__init__.py
elasticsearch_migrate/management/commands/__init__.py
elasticsearch_migrate/management/commands/migrate_docs.py
elasticsearch_migrate/migrations/__init__.py
elasticsearch_django_migrate-0.0.1.dist-info/LICENSE
elasticsearch_django_migrate-0.0.1.dist-info/METADATA
elasticsearch_django_migrate-0.0.1.dist-info/WHEEL
elasticsearch_django_migrate-0.0.1.dist-info/top_level.txt
elasticsearch_django_migrate-0.0.1.dist-info/RECORD
