Metadata-Version: 2.1
Name: elasticsearch-django-migrate
Version: 0.0.1
Summary: Migrate elasticsearch Document represented by python into Elasticsearch index
Home-page: https://github.com/amazinglzy/elasticsearch_migrate
Author: Li Zhiyuan
Author-email: forlearn_lzy@163.com
License: UNKNOWN
Platform: UNKNOWN
Classifier: Programming Language :: Python :: 3
Classifier: License :: OSI Approved :: MIT License
Classifier: Operating System :: OS Independent
Requires-Python: >=3.6
